strapy/__init__.py
strapy/main.py
strapy/strapy.py
strapy/utils.py
strapy-0.0.1.dist-info/LICENSE
strapy-0.0.1.dist-info/METADATA
strapy-0.0.1.dist-info/WHEEL
strapy-0.0.1.dist-info/entry_points.txt
strapy-0.0.1.dist-info/top_level.txt
strapy-0.0.1.dist-info/RECORD
