Metadata-Version: 2.1
Name: strapy
Version: 0.0.1
Summary: A framework for building out bootstrap utilities
Home-page: https://github.com/WilliamJohns/strapy
Author: William Johns
Author-email: will@wcj.dev
License: UNKNOWN
Project-URL: Bug Tracker, https://github.com/WilliamJohns/strapy/issues
Platform: UNKNOWN
Classifier: Programming Language :: Python :: 3
Classifier: License :: OSI Approved :: MIT License
Classifier: Operating System :: OS Independent
Requires-Python: >=3.6
License-File: LICENSE
